bin/package-build.sh
bin/package-publish-test.sh
bin/package-publish.sh
pytusk/__init__.py
pytusk/version.py
pytusk-0.0.2.dist-info/licenses/LICENSE
pytusk-0.0.2.dist-info/METADATA
pytusk-0.0.2.dist-info/WHEEL
pytusk-0.0.2.dist-info/top_level.txt
pytusk-0.0.2.dist-info/RECORD
