Metadata-Version: 2.4
Name: pytusk
Version: 0.0.2
Summary: Walrus client Python SDK
License: Apache-2.0
Keywords: software development kit,sui,blockchain
Classifier: Development Status :: 4 - Beta
Classifier: Intended Audience :: Developers
Classifier: Topic :: Software Development
Classifier: Topic :: Software Development :: Libraries
Classifier: Programming Language :: Python
Classifier: Operating System :: OS Independent
Classifier: License :: OSI Approved :: Apache Software License
Classifier: Programming Language :: Python :: 3.11
Classifier: Programming Language :: Python :: 3.12
Classifier: Programming Language :: Python :: 3 :: Only
Requires-Python: >=3.11
License-File: LICENSE
Dynamic: license-file
